torch_baidu_ctc/_C.cpython-36m-x86_64-linux-gnu.so
torch_baidu_ctc/__init__.py
torch_baidu_ctc/test.py
torch_baidu_ctc/libcudart-f7fdd8d7.so.9.0
torch_baidu_ctc-0.3.0.dist-info/METADATA
torch_baidu_ctc-0.3.0.dist-info/WHEEL
torch_baidu_ctc-0.3.0.dist-info/top_level.txt
torch_baidu_ctc-0.3.0.dist-info/RECORD
